lucky/__init__.py
lucky-0.0.1.dist-info/METADATA
lucky-0.0.1.dist-info/RECORD
lucky-0.0.1.dist-info/WHEEL
lucky-0.0.1.dist-info/top_level.txt
