Metadata-Version: 2.1
Name: lucky
Version: 0.0.1
Summary: Starspot maps with starry.
Home-page: https://github.com/rodluger/lucky
Author: Rodrigo Luger
Author-email: rodluger@gmail.com
License: MIT
Platform: UNKNOWN
